tsnmf/__init__.py
tsnmf/tsnmf.py
tsnmf-1.0.4.dist-info/LICENSE
tsnmf-1.0.4.dist-info/METADATA
tsnmf-1.0.4.dist-info/WHEEL
tsnmf-1.0.4.dist-info/top_level.txt
tsnmf-1.0.4.dist-info/RECORD
