Metadata-Version: 2.1
Name: tsnmf
Version: 1.0.4
Summary: Implementation of Topic-Supervised Non-Negative Matrix Factorization
Home-page: https://github.com/Vokturz/tsnmf-sparse
Author: Victor Navarro & Eduardo Graells
Author-email: victor.navarro@ug.uchile.cl
License: BSD 3-clause "New" or "Revised License"
Keywords: tsnmf nmf sparse
Platform: UNKNOWN
Classifier: Programming Language :: Python :: 3
Classifier: License :: OSI Approved :: BSD License
Classifier: Operating System :: OS Independent
Requires-Python: >=3.6
Requires-Dist: numpy
Requires-Dist: sklearn
Requires-Dist: scipy
